<?xml version="1.0" encoding="UTF-8"?>
<!-- Created by Kactus2 - Open source IP-Xact toolset -->
<!-- http://sourceforge.net/projects/kactus2/ -->
<!-- Date: 02.07.2012 -->
<!-- Time: 11:40:34 -->
<spirit:busDefinition xmlns:kactus2="http://funbase.cs.tut.fi/" xmlns:spirit="http://www.spiritconsortium.org/XMLSchema/SPIRIT/1.5" xmlns:xsi="http://www.w3.org/2001/XMLSchema-instance" xsi:schemaLocation="http://www.spiritconsortium.org/XMLSchema/SPIRIT/1.5 http://www.spiritconsortium.org/XMLSchema/SPIRIT/1.5/index.xsd">
	<spirit:vendor>TUT</spirit:vendor>
	<spirit:library>ip.hwp.communication</spirit:library>
	<spirit:name>hibi_ip_r3.busdef</spirit:name>
	<spirit:version>3.0</spirit:version>
	<spirit:directConnection>false</spirit:directConnection>
	<spirit:isAddressable>true</spirit:isAddressable>
</spirit:busDefinition>
